README
setup.py
pommons/__init__.py
pommons.egg-info/PKG-INFO
pommons.egg-info/SOURCES.txt
pommons.egg-info/dependency_links.txt
pommons.egg-info/top_level.txt