Metadata-Version: 1.0
Name: pommons
Version: 0.12
Summary: Some convenient Python boilerplates
Home-page: http://packages.python.org/pommons
Author: Adam Matan
Author-email: adam@matan.name
License: GPLv3
Keywords: Python commons
Platform: UNKNOWN
Classifier: Development Status :: 3 - Alpha
Classifier: Topic :: Utilities
Classifier: License :: OSI Approved :: GNU General Public License v3 (GPLv3)
